{
    "date": "201706082136",
    "channel": "C",
    "h_code": "38601",
    "h_ga1": "",
    "h_ga2": "",
    "h_name": "トヨタカローラ宮崎",
    "c_name": "noah",
    "w_type": "true",
    "h_logo": "true",
    "cp_type": "true",
    "b_plan": "true",
    "b_select": {
        "p_zanka": "1",
        "p_kanzen": "0"
    },
    "cv": {
        "catalog": {
            "btn": "true",
            "event_header_pc": "ga('send', 'event','noah','header_catalog', 'pc_ヘッダーリンク_カタログ",
            "event_header_sp": "ga('send', 'event','noah','header_catalog', 'sp_ヘッダーリンク_カタログ",
            "event_contents_pc": "ga('send', 'event','noah','contents_catalog', 'pc_コンテンツリンク_カタログ",
            "event_contents_sp": "ga('send', 'event','noah','contents_catalog', 'sp_コンテンツリンク_カタログ",
            "event_footer_pc": "ga('send', 'event','noah','footer_catalog', 'pc_フッターリンク_カタログ",
            "event_footer_sp": "ga('send', 'event','noah','footer_catalog', 'sp_フッターリンク_カタログ",
            "url": "https://toyota-dealers.jp/form.php?code=38601&page=kiyaku&genre=support&form_type=catalog&car_name=%E3%83%8E%E3%82%A2",
            "url_sp": "null"
        },
        "store": {
            "btn": "true",
            "event_header_pc": "ga('send', 'event','noah','header_store', 'pc_ヘッダーリンク_店舗検索",
            "event_header_sp": "ga('send', 'event','noah','header_store', 'sp_ヘッダーリンク_店舗検索",
            "event_contents_pc": "ga('send', 'event','noah','contents_store', 'pc_コンテンツリンク_店舗検索",
            "event_contents_sp": "ga('send', 'event','noah','contents_store', 'sp_コンテンツリンク_店舗検索",
            "event_footer_pc": "ga('send', 'event','noah','footer_store', 'pc_フッターリンク_店舗検索",
            "event_footer_sp": "ga('send', 'event','noah','footer_store', 'sp_フッターリンク_店舗検索",
            "url": "https://www.corolla-miyazaki.jp/store-list/",
            "url_sp": "null"
        },
        "shodan": {
            "btn": "true",
            "event_header_pc": "ga('send', 'event','noah','header_shodan', 'pc_ヘッダーリンク_商談予約",
            "event_header_sp": "ga('send', 'event','noah','header_shodan', 'sp_ヘッダーリンク_商談予約",
            "event_contents_pc": "ga('send', 'event','noah','contents_shodan', 'pc_コンテンツリンク_商談予約",
            "event_contents_sp": "ga('send', 'event','noah','contents_shodan', 'sp_コンテンツリンク_商談予約",
            "event_footer_pc": "ga('send', 'event','noah','footer_shodan', 'pc_フッターリンク_商談予約",
            "event_footer_sp": "ga('send', 'event','noah','footer_shodan', 'sp_フッターリンク_商談予約",
            "url": "https://toyota-dealers.jp/form.php?code=38601&page=kiyaku&genre=support&form_type=shodan&car_name=%E3%83%8E%E3%82%A2",
            "url_sp": "null"
        },
        "try": {
            "btn": "true",
            "event_header_pc": "ga('send', 'event','noah','header_try', 'pc_ヘッダーリンク_試乗",
            "event_header_sp": "ga('send', 'event','noah','header_try', 'sp_ヘッダーリンク_試乗",
            "event_contents_pc": "ga('send', 'event','noah','contents_try', 'pc_コンテンツリンク_試乗",
            "event_contents_sp": "ga('send', 'event','noah','contents_try', 'sp_コンテンツリンク_試乗",
            "event_footer_pc": "ga('send', 'event','noah','footer_try', 'pc_フッターリンク_試乗",
            "event_footer_sp": "ga('send', 'event','noah','footer_try', 'sp_フッターリンク_試乗",
            "url": "http://toyota.jp/service/dealer/spt/trial-list-car?CN=C&OFFICE_CD=38601",
            "url_sp": "null"
        },
        "online": {
            "btn": "true",
            "event_header_pc": "ga('send', 'event','noah','header_online', 'pc_ヘッダーリンク_見積り",
            "event_header_sp": "ga('send', 'event','noah','header_online', 'sp_ヘッダーリンク_見積り",
            "event_contents_pc": "ga('send', 'event','noah','contents_online', 'pc_コンテンツリンク_見積り",
            "event_contents_sp": "ga('send', 'event','noah','contents_online', 'sp_コンテンツリンク_見積り",
            "event_footer_pc": "ga('send', 'event','noah','footer_online', 'pc_フッターリンク_見積り",
            "event_footer_sp": "ga('send', 'event','noah','footer_online', 'sp_フッターリンク_見積り",
            "url": "http://toyota.jp/service/dealer_estimate/dc/top?SALE_OFFICE_CD=38601",
            "url_sp": "null"
        }
    },
    "h_url": "https://www.corolla-miyazaki.jp/",
    "h_url_sp": "null",
    "h_tag": "false",
    "cp": {
        "cp_name1": "true",
        "cp_name2": "新型ノアWEB試乗予約キャンペーン",
        "cp_detail1": "true",
        "cp_detail2": ["対象期間：2017年7月4日～8月31日","期間中、新型ノアのWEB試乗予約をしていただき店舗に店舗にて","ご試乗頂いたお客様に新型ノア プルバックミニカーをプレゼント！！"],
        "cp_caution1": "true",
        "cp_caution2": ["ミニカーは1組様1つまでとさせていただきます。","数に限りがございますので予めご了承ください。","試乗車は店舗間で入替をする場合がございます。ご希望がございましたらお電話にてお問い合わせください。"],
        "cp_img": {
            "num": "1",
            "cp_list0": "false",
            "cp_list1": "false",
            "cp_list2": "false",
            "cp_list3": "false",
            "cp_list4": "false",
            "cp_list5": "false",
            "cp_list6": "false",
            "cp_list7": "false",
            "cp_list8": "false",
            "cp_list9": "false",
            "cp_list10": "false",
            "cp_list11": "false",
            "cp_list12": "false",
            "cp_list13": "false",
            "cp_list14": "true",
            "cp_list15": "false",
            "cp_list16": "false",
            "cp_list17": "null",
            "cp_list18": "null"
        }
    },
    "zanka1": {
        "copy": ["カローラ宮崎【てげイージープラン】"],
        "grade": "HV-Si",
        "drive": "2WD",
        "capacity": "7人",
        "engine": "ハイブリッド",
        "payment": {
            "total": "3,269,160",
            "vehicle": "3,269,160",
            "acce": "0",
            "down": "650,000",
            "principal": "2,619,160",
            "pay_number": "60",
            "pay_period": "5",
            "rate": "3",
            "f_price": "19,345",
            "f_number": "1",
            "f_month": "10",
            "s_price": "18,500",
            "s_number": "48",
            "b_price": "80,000",
            "b_number": "10",
            "case1": "0",
            "case2": "0",
            "case3": "1,209,580",
            "result1": "2,357,345",
            "result2": "3,566,925"
        },
        "pay_caution": {
            "pay_caution1": "false",
            "pay_caution2": [
            null
            ],
            "pay_caution3": "null"
        },
        "order": "",
        "aera": ""
    },
    "zanka2": {
        "copy": [null],
        "grade": "null",
        "drive": "null",
        "capacity": "null",
        "engine": "null",
        "payment": {
            "total": "null",
            "vehicle": "null",
            "acce": "null",
            "down": "null",
            "principal": "null",
            "pay_number": "null",
            "pay_period": "null",
            "rate": "null",
            "f_price": "null",
            "f_number": "1",
            "f_month": "null",
            "s_price": "null",
            "s_number": "null",
            "b_price": "null",
            "b_number": "null",
            "case1": "null",
            "case2": "null",
            "case3": "null",
            "result1": "null",
            "result2": "null"
        },
        "pay_caution": {
            "pay_caution1": "false",
            "pay_caution2": [
            null
            ],
            "pay_caution3": "null"
        },
        "order": "",
        "aera": ""
    },
    "kanzen1": {
        "copy": [null],
        "grade": "null",
        "drive": "null",
        "capacity": "null",
        "engine": "null",
        "payment": {
            "total": "null",
            "vehicle": "null",
            "acce": "null",
            "down": "null",
            "principal": "null",
            "pay_number": "null",
            "pay_period": "null",
            "rate": "null",
            "f_price": "null",
            "f_number": "1",
            "f_month": "null",
            "s_price": "null",
            "s_number": "null",
            "b_price": "null",
            "b_number": "null",
            "result1": "null"
        },
        "pay_caution": {
            "pay_caution1": "false",
            "pay_caution2": [
            null
            ],
            "pay_caution3": "null"
        },
        "order": "",
        "aera": ""
    },
    "kanzen2": {
        "copy": [null],
        "grade": "null",
        "drive": "null",
        "capacity": "null",
        "engine": "null",
        "payment": {
            "total": "null",
            "vehicle": "null",
            "acce": "null",
            "down": "null",
            "principal": "null",
            "pay_number": "null",
            "pay_period": "null",
            "rate": "null",
            "f_price": "null",
            "f_number": "1",
            "f_month": "null",
            "s_price": "null",
            "s_number": "null",
            "b_price": "null",
            "b_number": "null",
            "result1": "null"
        },
        "pay_caution": {
            "pay_caution1": "false",
            "pay_caution2": [
            null
            ],
            "pay_caution3": "null"
        },
        "order": "",
        "aera": ""
    },
    "staff": {
        "name": "null",
        "template": "null",
        "comment": [
            null
        ]
    },
    "shoparea": {
        "area1": {
            "area_name": "null",
            "shop_name": [
                null
            ]
        },
        "area2": {
            "area_name": "null",
            "shop_name": [
                null
            ]
        },
        "area3": {
            "area_name": "null",
            "shop_name": [
                null
            ]
        },
        "area4": {
            "area_name": "null",
            "shop_name": [
                null
            ]
        },
        "area5": {
            "area_name": "null",
            "shop_name": [
                null
            ]
        },
        "area6": {
            "area_name": "null",
            "shop_name": [
                null
            ]
        }
    },
    "tpoint": {
        "select": "null",
        "comment": [
            null
        ]
    }
}

